pyargparse/__init__.py
pyargparse/parser/__init__.py
pyargparse/parser/base_parser.py
pyargparse/parser/cli_parser.py
pyargparse/parser/env_parser.py
pyargparse/parser/yml_parser.py
pyargparse/parser/tests/__init__.py
pyargparse/parser/tests/arg_emulator.py
pyargparse/parser/tests/test_correct_parser.py
pyargparse/parser/tests/test_incorrect_parser.py
pyargparse/types/__init__.py
pyargparse/types/type_operations.py
pyargparse-0.1.8.dist-info/LICENSE.md
pyargparse-0.1.8.dist-info/METADATA
pyargparse-0.1.8.dist-info/WHEEL
pyargparse-0.1.8.dist-info/top_level.txt
pyargparse-0.1.8.dist-info/RECORD
